seltz/__init__.py
seltz/client.py
seltz/exceptions.py
seltz/seltz.py
seltz/services/__init__.py
seltz/services/search_service.py
seltz_public_api/proto/v1/seltz_pb2.py
seltz_public_api/proto/v1/seltz_pb2.pyi
seltz_public_api/proto/v1/seltz_pb2_grpc.py
seltz-0.1.2.dist-info/METADATA
seltz-0.1.2.dist-info/WHEEL
seltz-0.1.2.dist-info/top_level.txt
seltz-0.1.2.dist-info/RECORD
