Metadata-Version: 2.4
Name: seltz
Version: 0.1.2
Summary: Seltz Python SDK for AI-powered search
Author-email: Seltz <support@seltz.ai>
Project-URL: Homepage, https://seltz.ai
Project-URL: Documentation, https://docs.seltz.ai
Project-URL: Repository, https://github.com/seltz-ai/seltz-python-sdk
Project-URL: Bug Tracker, https://github.com/seltz-ai/seltz-python-sdk/issues
Keywords: search,ai,sdk,api
Classifier: Development Status :: 4 - Beta
Classifier: Intended Audience :: Developers
Classifier: Programming Language :: Python :: 3
Classifier: Programming Language :: Python :: 3.10
Classifier: Programming Language :: Python :: 3.11
Classifier: Programming Language :: Python :: 3.12
Classifier: Programming Language :: Python :: 3.13
Classifier: Programming Language :: Python :: 3.14
Classifier: Topic :: Software Development :: Libraries :: Python Modules
Classifier: Topic :: Internet :: WWW/HTTP :: Indexing/Search
Requires-Python: >=3.9
Requires-Dist: grpcio>=1.76.0
Requires-Dist: protobuf>=6.33.1
